{
  "documents": [
    {
      "document_id": "fed-openmarket",
      "title": "Federal Reserve Open Market Operations Overview",
      "source": "https://www.federalreserve.gov/monetarypolicy/openmarket.htm",
      "content": "ï»¿ Federal Reserve Board - Open Market Operations Skip to main content An official website of the United States Government Here's how you know Official websites use .gov A .gov website belongs to an official government organization in the United States. Secure .gov websites use HTTPS A lock ( Lock Locked padlock icon ) or https:// means you've safely connected to the .gov website. Share sensitive information only on official, secure websites. Back to Home Board of Governors of the Federal Reserve System Stay Connected Federal Reserve Facebook Page Federal Reserve Instagram Page Federal Reserve YouTube Page Federal Reserve Flickr Page Federal Reserve LinkedIn Page Federal Reserve Threads Page Federal Reserve X Page Federal Reserve Bluesky Page Subscribe to RSS Subscribe to Email Recent Postings Calendar Publications Site Map A-Z index Careers FAQs Videos Contact Search Submit Search Button Advanced Toggle Dropdown Menu Board of Governors of the Federal Reserve System The Federal Reserve, the central bank of the United States, provides the nation with a safe, flexible, and stable monetary and financial system. Main Menu Toggle Button Sections Search Toggle Button Search Search Submit Button Submit About the Fed Structure of the Federal Reserve System The Fed Explained Board Members Advisory Councils Federal Reserve Banks Federal Reserve Bank and Branch Directors Federal Reserve Act Currency Board Meetings Board Votes Careers Do Business with the Board Holidays Observed - K.8 Ethics & Values Contact Requesting Information (FOIA) FAQs Economic Education Fed Financial Statements Financial Innovation News & Events Press Releases Speeches & Testimony Calendar Videos Photo Gallery Conferences Monetary Policy Federal Open Market Committee About the FOMC Meeting calendars and information Transcripts and other historical materials FAQs Monetary Policy Principles and Practice Notes Policy Implementation Policy Normalization Policy Tools Reports Monetary Policy Report Beige Book Federal Reserve Balance Sheet Developments Review of Monetary Policy Strategy, Tools, and Communications Overview Supervision & Regulation Supervision Community Banks Regional Banks and Foreign Banks with U.S. Assets Large Banks and Large Foreign Banks Global Systemically Important Banks Financial Market Utilities Consumer Compliance Resources for Supervised Institutions Reports Federal Reserve Supervision and Regulation Report Reporting Forms Recent Reporting Form Updates Information Collections Under Review Financial Statements Securities Exchange Act of 1934 Applications/Structure Change FFIEC Municipal and Government Securities Activities Monitoring Micro Data Reference Manual Legal Developments Enforcement Actions and Legal Developments Mergers, Acquisitions, and Other Applications Process Filing Information Board and Reserve Bank Actions Supervision and Regulation Letters By Year By Topic Regulatory and Policy Resources Federal Reserve Act Bank Holding Company Act Regulations Supervision Manuals Federal Reserve Regulatory Service Disaster Preparedness and Recovery Resources Banking and Data Structure Beneficial Ownership Reports Large Commercial Banks Minority Depository Institutions U.S. Offices of Foreign Entities Financial Holding Companies Interstate Branching Securities Underwriting and Dealing Subsidiaries State Member Banks Supervised by the Federal Reserve Financial Stability Financial Stability Assessments About Financial Stability Types of Financial System Vulnerabilities & Risks Monitoring Risk Across the Financial System Proactive Monitoring of Markets & Institutions Financial Stability & Stress Testing Financial Stability Coordination & Actions Responding to Financial System Emergencies Cooperation on Financial Stability Reports Financial Stability Report Payment Systems Regulations & Statutes Regulation CC (Availability of Funds and Collection of Checks) Regulation II (Debit Card Interchange Fees and Routing) Regulation HH (Financial Market Utilities) Other Regulations and Statutes Payment Policies Federal Reserve's Key Policies for the Provision of Financial Services Guidelines for Evaluating Joint Account Requests Overnight Overdrafts Payment System Risk Sponsorship for Priority Telecommunication Services Reserve Bank Payment Services & Data Automated Clearinghouse Services Check Services Currency and Coin Services Daylight Overdrafts and Fees FedNow ® Service Fedwire Funds Services Fedwire Securities Services Fiscal Agency Services Master Account and Services Database National Settlement Service Financial Market Utilities & Infrastructures Supervision & Oversight of Financial Market Infrastructures Designated Financial Market Utilities International Standards for Financial Market Infrastructures Research, Reports, & Committees Federal Reserve Payments Study (FRPS) Payments Research Reports Payments System Policy Advisory Committee Economic Research Meet the Researchers Working Papers and Notes Finance and Economics Discussion Series (FEDS) FEDS Notes International Finance Discussion Papers (IFDP) Data, Models and Tools Economic Research Data FRB/US Model Estimated Dynamic Optimization (EDO) Model Survey of Consumer Finances (SCF) Data Data Download Program Bank Assets and Liabilities Aggregate Reserves of Depository Institutions and the Monetary Base - H.3 Assets and Liabilities of Commercial Banks in the U.S. - H.8 Assets and Liabilities of U.S. Branches and Agencies of Foreign Banks Charge-Off and Delinquency Rates on Loans and Leases at Commercial Banks Senior Financial Officer Survey Senior Loan Officer Opinion Survey on Bank Lending Practices Bank Structure Data Large Commercial Banks Minority Depository Institutions Structure and Share Data for the U.S. Offices of Foreign Banks Business Finance Commercial Paper Finance Companies - G.20 New Security Issues, State and Local Governments New Security Issues, U.S. Corporations Dealer Financing Terms Senior Credit Officer Opinion Survey on Dealer Financing Terms Exchange Rates and International Data Foreign Exchange Rates - H.10/G.5 International Summary Statistics Securities Holdings and Transactions Statistics Reported by Banks and Other Financial Firms in the United States Structure and Share Data for U.S. Offices of Foreign Banks Financial Accounts Financial Accounts of the United States - Z.1 Household Finance Consumer Credit - G.19 Household Debt Service Ratios Mortgage Debt Outstanding Survey of Consumer Finances (SCF) Survey of Household Economics and Decisionmaking Industrial Activity Industrial Production and Capacity Utilization - G.17 Interest Rates Selected Interest Rates - H.15 Micro Data Reference Manual (MDRM) Micro and Macro Data Collections Money Stock and Reserve Balances Factors Affecting Reserve Balances - H.4.1 Money Stock Measures - H.6 Other Yield Curve Models and Data Consumers & Communities Regulations Community Reinvestment Act (CRA) All Regulations SupervisionÂ & Enforcement CA Letters Enforcement Actions Independent Foreclosure Review Community Development Housing and Neighborhood Revitalization Small Business and Entrepreneurship Employment and Workforce Development Community Development Finance Rural Community and Economic Development Conferences ResearchÂ & Analysis Survey of Household Economics and Decisionmaking Research Publications & Data Analysis Community Advisory Council Resources for Consumers Frauds and Scams Mortgage and Foreclosure Resources Federal Reserve Community Development Resources Home Monetary Policy Policy Tools Policy Tools Open Market Operations Open market operations (OMOs)--the purchase and sale of securities in the open market by a central bank--are a key tool used by the Federal Reserve in the implementation of monetary policy. The short-term objective for open market operations is specified by the Federal Open Market Committee (FOMC). Before the global financial crisis, the Federal Reserve used OMOs to adjust the supply of reserve balances so as to keep the federal funds rate--the interest rate at which depository institutions lend reserve balances to other depository institutions overnight--around the target established by the FOMC. The Federal Reserve's approach to the implementation of monetary policy has evolved considerably since the financial crisis, and particularly so since late 2008 when the FOMC established a near-zero target range for the federal funds rate. From the end of 2008 through October 2014, the Federal Reserve greatly expanded its holding of longer-term securities through open market purchases with the goal of putting downward pressure on longer-term interest rates and thus supporting economic activity and job creation by making financial conditions more accommodative. During the policy normalization process that commenced in December 2015, the Federal Reserve first used overnight reverse repurchase agreements (ON RRPs)--a type of OMO--as a supplementary policy tool, as necessary, to help control the federal funds rate and keep it in the target range set by the FOMC. In September 2019, the Federal Reserve used term and overnight repurchase agreements (repo) to ensure that the supply of reserves remain ample even during periods of sharp increases in non-reserve liabilities, and to mitigate the risk of money market pressures that could adversely affect policy implementation. The Federal Reserve continued to offer overnight repos and, amid the COVID-related stress around March 2020, term and overnight repos played an important role in ensuring that the supply of reserves remained ample and supporting the smooth functioning of short-term U.S. dollar funding markets. Since 2021, Federal Reserve has conducted domestic standing repo (SRP) operations against eligible securities. SRP operations limit upward pressure and help provide a ceiling on rates to support the monetary policy implementation and smooth market functioning. For additional information, see: http://www.federalreserve.gov/monetarypolicy/bst_openmarketops.htm The Federal Reserve Bank of New York publishes a detailed explanation of OMOs each year in its Annual Report . For a description of open market operations during the 1990s, see the article in the Federal Reserve Bulletin (102 KB PDF). For additional information on how the Federal Reserve will use ON RRPs during the policy normalization process, see: http://www.federalreserve.gov/monetarypolicy/overnight-reverse-repurchase-agreements.htm FOMC's target federal funds rate or range, change (basis points) and level 2025 | 2024 | 2023 | 2022 | 2020 | 2019 | 2018 | 2017 | 2016 | 2015 | 2008 | 2007 | 2006 | 2005 | 2004 | 2003 | Historical Archive 2025 Date Increase Decrease Level (%) December 11 0 25 3.50-3.75 October 30 0 25 3.75-4.00 September 18 0 25 4.00-4.25 Back to year navigation 2024 Date Increase Decrease Level (%) December 19 0 25 4.25-4.50 November 8 0 25 4.50-4.75 September 19 0 50 4.75-5.00 Back to year navigation 2023 Date Increase Decrease Level (%) July 27 25 0 5.25-5.50 May 4 25 0 5.00-5.25 March 23 25 0 4.75-5.00 February 2 25 0 4.50-4.75 Back to year navigation 2022 Date Increase Decrease Level (%) December 15 50 0 4.25-4.50 November 3 75 0 3.75-4.00 September 22 75 0 3.00-3.25 July 28 75 0 2.25-2.50 June 16 75 0 1.50-1.75 May 5 50 0 0.75-1.00 March 17 25 0 0.25-0.50 Back to year navigation 2020 Date Increase Decrease Level (%) March 16 0 100 0-0.25 March 4 * 0 50 1.00-1.25 Back to year navigation 2019 Date Increase Decrease Level (%) October 31 0 25 1.50-1.75 September 19 0 25 1.75-2.00 August 1 0 25 2.00-2.25 Back to year navigation 2018 Date Increase Decrease Level (%) December 20 25 0 2.25-2.50 September 27 25 0 2.00-2.25 June 14 25 0 1.75-2.00 March 22 25 0 1.50-1.75 Back to year navigation 2017 Date Increase Decrease Level (%) December 14 25 0 1.25-1.50 June 15 25 0 1.00-1.25 March 16 25 0 0.75-1.00 Back to year navigation 2016 Date Increase Decrease Level (%) December 15 25 0 0.50-0.75 Back to year navigation 2015 Date Increase Decrease Level (%) December 17 25 0 0.25-0.50 Back to year navigation 2008 Date Increase Decrease Level (%) December 16 ... 75-100 0-0.25 October 29 ... 50 1.00 October 8 ... 50 1.50 April 30 ... 25 2.00 March 18 ... 75 2.25 January 30 ... 50 3.00 January 22 ... 75 3.50 Back to year navigation 2007 Date Increase Decrease Level (%) December 11 ... 25 4.25 October 31 ... 25 4.50 September 18 ... 50 4.75 Back to year navigation 2006 Date Increase Decrease Level (%) June 29 25 ... 5.25 May 10 25 ... 5.00 March 28 25 ... 4.75 January 31 25 ... 4.50 Back to year navigation 2005 Date Increase Decrease Level (%) December 13 25 ... 4.25 November 1 25 ... 4.00 September 20 25 ... 3.75 August 9 25 ... 3.50 June 30 25 ... 3.25 May 3 25 ... 3.00 March 22 25 ... 2.75 February 2 25 ... 2.50 Back to year navigation 2004 Date Increase Decrease Level (%) December 14 25 ... 2.25 November 10 25 ... 2.00 September 21 25 ... 1.75 August 10 25 ... 1.50 June 30 25 ... 1.25 Back to year navigation 2003 Date Increase Decrease Level (%) June 25 ... 25 1.00 Back to year navigation Basis points: 1/100 percentage point Return to Text * On July 10, 2024, this date was corrected from March 3, 2020, to March 4, 2020. Return to Text Back to Top Last Update: December 12, 2025 Board of Governors of the Federal Reserve System About the Fed News & Events Monetary Policy Supervision & Regulation Financial Stability Payment Systems Economic Research Data Consumers & Communities Connect with the Board Tools and Information Contact Publications Freedom of Information (FOIA) Office of Inspector General Budget & Performance | Audit No FEAR Act Español Website Policies | Privacy Program Accessibility Stay Connected Federal Reserve Facebook Page Federal Reserve Instagram Page Federal Reserve YouTube Page Federal Reserve Flickr Page Federal Reserve LinkedIn Page Federal Reserve Threads Page Link to Federal Reserve X Page Link to Federal Reserve Bluesky Page Subscribe to RSS Subscribe to Email Board of Governors of the Federal Reserve System 20th Street and Constitution Avenue N.W., Washington, DC 20551"
    },
    {
      "document_id": "fed-fomc",
      "title": "Federal Open Market Committee (FOMC) Overview",
      "source": "https://www.federalreserve.gov/monetarypolicy/fomc.htm",
      "content": "ï»¿ The Fed - Federal Open Market Committee Skip to main content An official website of the United States Government Here's how you know Official websites use .gov A .gov website belongs to an official government organization in the United States. Secure .gov websites use HTTPS A lock ( Lock Locked padlock icon ) or https:// means you've safely connected to the .gov website. Share sensitive information only on official, secure websites. Back to Home Board of Governors of the Federal Reserve System Stay Connected Federal Reserve Facebook Page Federal Reserve Instagram Page Federal Reserve YouTube Page Federal Reserve Flickr Page Federal Reserve LinkedIn Page Federal Reserve Threads Page Federal Reserve X Page Federal Reserve Bluesky Page Subscribe to RSS Subscribe to Email Recent Postings Calendar Publications Site Map A-Z index Careers FAQs Videos Contact Search Submit Search Button Advanced Toggle Dropdown Menu Board of Governors of the Federal Reserve System The Federal Reserve, the central bank of the United States, provides the nation with a safe, flexible, and stable monetary and financial system. Main Menu Toggle Button Sections Search Toggle Button Search Search Submit Button Submit About the Fed Structure of the Federal Reserve System The Fed Explained Board Members Advisory Councils Federal Reserve Banks Federal Reserve Bank and Branch Directors Federal Reserve Act Currency Board Meetings Board Votes Careers Do Business with the Board Holidays Observed - K.8 Ethics & Values Contact Requesting Information (FOIA) FAQs Economic Education Fed Financial Statements Financial Innovation News & Events Press Releases Speeches & Testimony Calendar Videos Photo Gallery Conferences Monetary Policy Federal Open Market Committee About the FOMC Meeting calendars and information Transcripts and other historical materials FAQs Monetary Policy Principles and Practice Notes Policy Implementation Policy Normalization Policy Tools Reports Monetary Policy Report Beige Book Federal Reserve Balance Sheet Developments Review of Monetary Policy Strategy, Tools, and Communications Overview Supervision & Regulation Supervision Community Banks Regional Banks and Foreign Banks with U.S. Assets Large Banks and Large Foreign Banks Global Systemically Important Banks Financial Market Utilities Consumer Compliance Resources for Supervised Institutions Reports Federal Reserve Supervision and Regulation Report Reporting Forms Recent Reporting Form Updates Information Collections Under Review Financial Statements Securities Exchange Act of 1934 Applications/Structure Change FFIEC Municipal and Government Securities Activities Monitoring Micro Data Reference Manual Legal Developments Enforcement Actions and Legal Developments Mergers, Acquisitions, and Other Applications Process Filing Information Board and Reserve Bank Actions Supervision and Regulation Letters By Year By Topic Regulatory and Policy Resources Federal Reserve Act Bank Holding Company Act Regulations Supervision Manuals Federal Reserve Regulatory Service Disaster Preparedness and Recovery Resources Banking and Data Structure Beneficial Ownership Reports U.S. Domestically Chartered Commercial Banks Minority Depository Institutions U.S. Offices of Foreign Entities Financial Holding Companies Interstate Branching Securities Underwriting and Dealing Subsidiaries State Member Banks Supervised by the Federal Reserve Financial Stability Financial Stability Assessments About Financial Stability Types of Financial System Vulnerabilities & Risks Monitoring Risk Across the Financial System Proactive Monitoring of Markets & Institutions Financial Stability & Stress Testing Financial Stability Coordination & Actions Responding to Financial System Emergencies Cooperation on Financial Stability Reports Financial Stability Report Payment Systems Regulations & Statutes Regulation CC (Availability of Funds and Collection of Checks) Regulation II (Debit Card Interchange Fees and Routing) Regulation HH (Financial Market Utilities) Other Regulations and Statutes Payment Policies Federal Reserve's Key Policies for the Provision of Financial Services Guidelines for Evaluating Joint Account Requests Overnight Overdrafts Payment System Risk Sponsorship for Priority Telecommunication Services Reserve Bank Payment Services & Data Automated Clearinghouse Services Check Services Currency and Coin Services Daylight Overdrafts and Fees FedNow ® Service Fedwire Funds Services Fedwire Securities Services Fiscal Agency Services Master Account and Services Database National Settlement Service Financial Market Utilities & Infrastructures Supervision & Oversight of Financial Market Infrastructures Designated Financial Market Utilities International Standards for Financial Market Infrastructures Research, Reports, & Committees Federal Reserve Payments Study (FRPS) Payments Research Reports Payments System Policy Advisory Committee Economic Research Meet the Researchers Working Papers and Notes Finance and Economics Discussion Series (FEDS) FEDS Notes International Finance Discussion Papers (IFDP) Data, Models and Tools Economic Research Data FRB/US Model Estimated Dynamic Optimization (EDO) Model Survey of Consumer Finances (SCF) Data Data Download Program Bank Assets and Liabilities Aggregate Reserves of Depository Institutions and the Monetary Base - H.3 Assets and Liabilities of Commercial Banks in the U.S. - H.8 Assets and Liabilities of U.S. Branches and Agencies of Foreign Banks Charge-Off and Delinquency Rates on Loans and Leases at Commercial Banks Senior Financial Officer Survey Senior Loan Officer Opinion Survey on Bank Lending Practices Bank Structure Data U.S. Domestically Chartered Commercial Banks Minority Depository Institutions Structure and Share Data for the U.S. Offices of Foreign Banks Business Finance Commercial Paper Finance Companies - G.20 New Security Issues, State and Local Governments New Security Issues, U.S. Corporations Dealer Financing Terms Senior Credit Officer Opinion Survey on Dealer Financing Terms Exchange Rates and International Data Foreign Exchange Rates - H.10/G.5 International Summary Statistics Securities Holdings and Transactions Statistics Reported by Banks and Other Financial Firms in the United States Structure and Share Data for U.S. Offices of Foreign Banks Financial Accounts Financial Accounts of the United States - Z.1 Household Finance Consumer Credit - G.19 Household Debt Service Ratios Mortgage Debt Outstanding Survey of Consumer Finances (SCF) Survey of Household Economics and Decisionmaking Industrial Activity Industrial Production and Capacity Utilization - G.17 Interest Rates Selected Interest Rates - H.15 Micro Data Reference Manual (MDRM) Micro and Macro Data Collections Money Stock and Reserve Balances Factors Affecting Reserve Balances - H.4.1 Money Stock Measures - H.6 Other Yield Curve Models and Data Consumers & Communities Regulations Community Reinvestment Act (CRA) All Regulations SupervisionÂ & Enforcement CA Letters Enforcement Actions Independent Foreclosure Review Community Development Housing and Neighborhood Revitalization Small Business and Entrepreneurship Employment and Workforce Development Community Development Finance Rural Community and Economic Development Conferences ResearchÂ & Analysis Survey of Household Economics and Decisionmaking Research Publications & Data Analysis Community Advisory Council Resources for Consumers Frauds and Scams Mortgage and Foreclosure Resources Federal Reserve Community Development Resources Home Monetary Policy Federal Open Market Committee About the FOMC Meeting calendars and information Transcripts and other historical materials FAQs About the FOMC FOMC Search Search all FOMC materials FOMC Document Filter Advanced Search FOMC calendar FOMC Longer-Run Goals and Monetary Policy Strategy (PDF) Addendum to FOMC Policy Normalization Principles and Plans Recent Statement | Recent Minutes FOMC Calendar Recent FOMC press conference March 18, 2026 Accessible Keys for Video [Space Bar] toggles play/pause; [Right/Left Arrows] seeks the video forwards and back (5 sec ); [Up/Down Arrows] increase/decrease volume; [M] toggles mute on/off; [F] toggles fullscreen on/off (Except IE 11); The [Tab] key may be used in combination with the [Enter/Return] key to navigate and activate control buttons, such as caption on/off. Press Conference Materials Opening Statement Transcript (PDF) FOMC Transcripts and other historical materials 2020 FOMC Historical Documents FAQs Related Content Guide to the Summary of Economic Projections The term \"monetary policy\" refers to the actions undertaken by a central bank, such as the Federal Reserve, to influence the availability and cost of money and credit to help promote national economic goals. The Federal Reserve Act of 1913 gave the Federal Reserve responsibility for setting monetary policy. The Federal Reserve controls the three tools of monetary policy-- open market operations , the discount rate , and reserve requirements . The Board of Governors of the Federal Reserve System is responsible for the discount rate and reserve requirements, and the Federal Open Market Committee is responsible for open market operations. Using the three tools, the Federal Reserve influences the demand for, and supply of, balances that depository institutions hold at Federal Reserve Banks and in this way alters the federal funds rate. The federal funds rate is the interest rate at which depository institutions lend balances at the Federal Reserve to other depository institutions overnight. Changes in the federal funds rate trigger a chain of events that affect other short-term interest rates, foreign exchange rates, long-term interest rates, the amount of money and credit, and, ultimately, a range of economic variables, including employment, output, and prices of goods and services. Structure of the FOMC The Federal Open Market Committee (FOMC) consists of twelve members--the seven members of the Board of Governors of the Federal Reserve System; the president of the Federal Reserve Bank of New York; and four of the remaining eleven Reserve Bank presidents, who serve one-year terms on a rotating basis. The rotating seats are filled from the following four groups of Banks, one Bank president from each group: Boston, Philadelphia, and Richmond; Cleveland and Chicago; Atlanta, St. Louis, and Dallas; and Minneapolis, Kansas City, and San Francisco. Nonvoting Reserve Bank presidents attend the meetings of the Committee, participate in the discussions, and contribute to the Committee's assessment of the economy and policy options. The FOMC holds eight regularly scheduled meetings per year. At these meetings, the Committee reviews economic and financial conditions, determines the appropriate stance of monetary policy, and assesses the risks to its long-run goals of price stability and sustainable economic growth. For more information about the FOMC and monetary policy, see the \" Monetary Policy \" section of The Fed Explained: What the Central Bank Does . FOMC Rules and Authorizations are available online . 2026 Committee Members Jerome H. Powell , Board of Governors, Chair John C. Williams , New York, Vice Chair Michael S. Barr , Board of Governors Michelle W. Bowman , Board of Governors Lisa D. Cook , Board of Governors Beth M. Hammack , Cleveland Philip N. Jefferson , Board of Governors Neel Kashkari , Minneapolis Lorie K. Logan , Dallas Stephen I. Miran , Board of Governors Anna Paulson , Philadelphia Christopher J. Waller , Board of Governors Alternate Members Thomas I. Barkin , Richmond Mary C. Daly , San Francisco Austan D. Goolsbee , Chicago Sushmita Shukla , First Vice President, New York Cheryl Venable , Interim President, Atlanta Federal Reserve Bank Rotation on the FOMC Committee membership changes at the first regularly scheduled meeting of the year. 2027 2028 2029 Members New York Chicago Richmond Atlanta San Francisco New York Cleveland Boston St. Louis Kansas City New York Chicago Philadelphia Dallas Minneapolis Alternate Members New York â Cleveland Boston St. Louis Kansas City New York â Chicago Philadelphia Dallas Minneapolis New York â Cleveland Richmond Atlanta San Francisco â For the Federal Reserve Bank of New York, the First Vice President is the alternate for the President. Return to table For additional information, please use the FOMC FOIA request form . Back to Top Last Update: April 08, 2026 Board of Governors of the Federal Reserve System About the Fed News & Events Monetary Policy Supervision & Regulation Financial Stability Payment Systems Economic Research Data Consumers & Communities Connect with the Board Tools and Information Contact Publications Freedom of Information (FOIA) Office of Inspector General Budget & Performance | Audit No FEAR Act Español Website Policies | Privacy Program Accessibility Stay Connected Federal Reserve Facebook Page Federal Reserve Instagram Page Federal Reserve YouTube Page Federal Reserve Flickr Page Federal Reserve LinkedIn Page Federal Reserve Threads Page Link to Federal Reserve X Page Link to Federal Reserve Bluesky Page Subscribe to RSS Subscribe to Email Board of Governors of the Federal Reserve System 20th Street and Constitution Avenue N.W., Washington, DC 20551"
    },
    {
      "document_id": "ecb-mopo-overview",
      "title": "ECB Overview of Monetary Policy and Markets",
      "source": "https://www.ecb.europa.eu/mopo/html/index.en.html",
      "content": "Overview of monetary policy and markets Skip to: Skip to navigation Skip to content Skip to footer EN Български Čeština Dansk Deutsch Eλληνικά English Español Eesti keel Suomi Français Gaeilge Hrvatski Magyar Italiano Lietuvių Latviešu Malti Nederlands Polski Português Română Slovenčina Slovenščina Svenska Menu Monetary policy & markets Monetary policy & markets Our monetary policy strategy, the tools we use and the impact they have Overview of monetary policy and markets Quick links What is monetary policy? Strategy review Asset purchase programmes Latest monetary policy press conference 19 March 2026 Introduction Benefits of price stability Scope of monetary policy Transmission mechanism Decisions, statements & accounts Monetary policy strategy Strategy review Medium-term orientation Two per cent inflation target Economic, monetary and financial analysis Economic analysis Monetary and financial analysis Instruments Open market operations TLTROs Asset purchase programmes Securities lending Pandemic emergency purchase programme Standing facilities Minimum reserves Two-tier system International market operations Euro central bank liquidity lines Emergency liquidity assistance (ELA) Liquidity analysis Collateral Eligibility criteria and assessment Marketable assets Non-marketable assets List of eligible marketable assets User guide Collateral management Eligible SSSs Eligible links Eligible triparty agents Risk mitigation ECAF Risk control Haircut categories Valuation Loan-level requirements Data templates Eligibility requirements Frequently asked questions Contacts Structure of the euro area economy Economic policy Fiscal policies External trade Effective exchange rates Financial structure Financial markets Financial intermediaries Economic diversity Labour market Market contact groups Bond market (BMCG) Money market (MMCG) Debt Issuance Market Contact Group (DIMCG) ECB Operations managers group (ECB OMG) Foreign exchange (FXCG) Institutional Investor Dialogue (IID) Monetary Analysis Contact Group (MACG) Payments & financial stability Payments & financial stability Insights into our work on financial stability and payments and market infrastructures Overview of payments and financial stability Quick links Digital euro Payments news & events Market contact groups TARGET professional use documents and links Latest Financial Stability Review 26 November 2025 Payments TARGET Services Shared features T2 Facts and figures Governance T2S Governance Facts and figures Pricing TIPS Cross-border payments Governance Facts and figures Onboarding ECMS Pontes Governance TARGET professional use documents & links Shared features documents & links T2 documents & links T2S documents & links TIPS documents & links ECMS documents & links Pontes documents & links Tokenisation and DLT Appia Exploratory work Retail payments Retail payments strategy ECB as a catalyst SEPA Instant payments Market contact groups Collateral management harmonisation SCoRE Implementation FAQ AMI-SeCo Cyber resilience Financial market infrastructures TIBER-EU Euro Cyber Resilience Board Oversight Payment systems TARGET2-Securities Electronic payments Securities settlement systems and central counterparties Critical service providers Correspondent and custodian banks SecuRe Pay forum Reserve management services Key aspects Range of services Cash professionals Cash handling Authentication devices Recirculation of banknotes Common detector interface specifications Banknote manufacturer accreditation Financial stability Introduction to financial stability Macroprudential Measures Financial stability contact groups Statistics Statistics Access to all ECB statistics and background information Overview of ECB statistics Quick links Key figures ECB Data Portal Statistical releases PRESS RELEASE - ECB launches pilot project for research access to confidential statistical data 13 March 2025 Frequently accessed Euro exchange rates Key ECB interest rates Euro short-term rate (€STR) Interest rate benchmarks Working group on euro risk-free rates Inflation Euro area yield curves All statistics & background All key statistics All data services Data reporting & standards Governance and quality framework Co-operation and standards Banks’ data reporting AnaCredit AnaCredit Q&A Public consultations Banking industry dialogue on ESCB statistics and integrated reporting SDMX – statistical data exchange model INEXDA - granular data network The euro The euro All you need to know about our common currency Overview of the euro Quick links Cash professionals Banknote and coins statistics Euro exchange rates Redesign process of our future banknotes Digital euro What it is Digital euro and privacy How it works Why we need it Innovation platform Pilot Timeline and progress In-depth information Governance and stakeholder engagement Technical documents and research Scheme rulebook Frequently asked questions Cash The Eurosystem cash strategy The role of cash Issuance and circulation Access to and acceptance of cash Frequently asked questions Banknotes Future banknotes Redesign process Current banknotes Denominations Design elements Security features Anti-counterfeiting Banknote production and stocks Damaged and inked-stained banknotes Environment, health and safety Product environmental footprint Research and development Images and reproduction rules Information and training materials Coins €2 €1 50 cent 20 cent 10 cent 5 cent 2 cent 1 cent Common sides €2 commemorative coins Security features Collector coins Joining the euro area Bulgaria (2026) Croatia (2023) Lithuania (2015) Latvia (2014) Estonia (2011) Slovakia (2009) Cyprus (2008) Malta (2008) Slovenia (2007) Initial changeover (2002) Exchanging national cash Austria Belgium Bulgaria Croatia Cyprus Estonia Finland France Germany Greece Ireland Latvia Italy Lithuania Luxembourg Malta The Netherlands Portugal Slovakia Slovenia Spain Visually impaired people Research Research In-depth studies and expert analyses covering diverse topics and fields Overview of ECB research Quick links Conferences & seminars Opportunities for researchers Research Bulletin Economic research Research agenda Monetary policy, strategy and implementation Fiscal policy and governance within EMU International macro and finance Real sector and microeconomic analysis Forecasting and business cycle analysis Macro-finance, systemic risk and macroprudential policy Financial institutions, microprudential policy, financial markets and payments Opportunities for researchers Wim Duisenberg Fellowship Regular Research Visitors Lamfalussy Fellowship Summer Research Graduate Programme Student Research Traineeship Programme Legal Research Legal conferences and seminars Legal Research Programme Research papers Papers by authors ECB researchers Research networks News & publications News & Publications Browse all news & publications News Press releases Statistical releases Speeches Interviews The ECB Blog Podcasts & webcasts Payments news & events Press hub Publications Governing Council decisions Monetary policy decisions Other decisions Monetary policy accounts Economic Bulletin Articles Focus Monthly Bulletin Macroeconomic projections Annual reports & financial statements Annual Report Annual Accounts Eurosystem balance sheet Monetary policy operations Weekly financial statements Disaggregated data Financial stability publications Financial Stability Review Special features & boxes Macroprudential Bulletin Research publications Research Bulletin Working papers Discussion papers Occasional papers Legal working papers Statistics papers Other publications Letters to MEPs Convergence Report International Role of the Euro Events & calendars Monetary policy press conference Monetary policy statements Monetary policy statements at a glance Conferences & seminars Forum on Central Banking Young Economist Prize Past editions Civil society engagement Calendars Weekly schedule Meetings of the Governing Council and the General Council Statistical calendars Money, banking and financial markets Euro area economic and financial developments by institutional sector External transactions and positions Prices, output, demand and labour Government finance Supervisory and prudential statistics Eurosystem's tender operations Reserve maintenance period ECB banking supervision About us About us All about us Our leadership Executive Board Governing Council General Council Supervisory Board Our organisation ECB, ESCB and the Eurosystem ECB mission Eurosystem mission Strategic intents Organisational principles Our tasks and responsibilities Monetary policy Statistics Financial stability and macroprudential policy Our tasks Strategy Institutional framework Banknotes Payments & securities European relations European cooperation EMU economic governance International affairs International relations and analysis International central bank cooperation Foreign reserves and own funds Foreign exchange operations Organisation chart of the ECB Capital subscription Corporate governance Eurosystem financial literacy network Our values Independence Transparency Accountability Ethics – working with integrity Ethics Network of Multilateral Organizations (ENMO) Our history, arts and culture Our history 25 years of the ECB Economic and Monetary Union EU enlargement European Union Archives Committee of Governors European Monetary Cooperation Fund Delors Committee European Monetary Institute European Central Bank Arts and culture Our legal framework EUR-Lex - Frequently asked questions Institutional framework Climate change and the ECB Our climate and nature plan Climate-related financial disclosures Managing climate-related risks Supporting the green transition Fostering wider action Our approach Environmental protection Climate Insurance Protection Gap Sanctions imposed by the ECB Procurement Tenders Archive Electronic tendering system Access to documents Public Register of Documents Contacts Address ECB public holidays ECB & You ECB & You All about ECB & You Explainers Key things to know about the ECB ECB and beyond Our currency, the euro Making payments Monetary policy Unconventional monetary policy instruments Banking supervision Climate change and the ECB Test your knowledge Youth initiatives Girls' IT Bootcamp Financial literacy in Europe The gender gap in financial literacy Everyone needs stability ECB & You broadcasts ECB in Frankfurt Ask us Visit us Main building Careers Careers All about careers Vacancies Who we are About the ECB Meet our people Life in Frankfurt Why we value diversity Women@ECB Diversity networks What we offer Benefits & rewards Contract types Fixed-term Short-term ESCB/IO Other Traineeship Graduate programme ECB Scholarship for Women ECB Scholarship for Ukrainian graduates How you can join us How to apply How we hire You have been selected, what next? Fixed-term employee Short-term employee Trainee Cost-free secondee FAQs Search Menu ANYTIME PAST MONTH PAST YEAR Search Options Image Preview Sort by ANYTIME PAST MONTH PAST YEAR Suggestions Home Media Explainers Research & Publications Statistics Monetary Policy The €uro Payments & Markets Careers Suggestions Sort by Relevance Date Overview of monetary policy and markets Price stability is the best contribution that monetary policy can make to economic growth Our main aim at the ECB is price stability. We serve people living in the euro area by working to preserve the value of the euro. In this section you can learn about our policy strategy, the tools we use and the impact they have on your day-to-day life. We also follow the financial markets. This gives us information for our core task of keeping prices stable, which contributes to economic growth. Monetary policy decisions We take decisions on monetary policy every six weeks – determining what should be done to keep inflation at our 2% target. Right after the decisions are taken, the President and Vice-President explain them in detail in a press conference. Monetary policy decisions and more Monetary policy statement We take decisions on monetary policy every six weeks – determining what should be done to keep inflation under control. Our visual statement explains this in short and easy-to-understand language. Our monetary policy statement at a glance Tools and policy measures Our monetary policy influences how much you have to pay to borrow and how much interest you receive on your savings. We steer interest rates with the aim of achieving price stability in the euro area. Find out how our tools and measures work. More information on our tools Monetary operations In addition to setting key interest rates, we also conduct open market operations. Check out the latest information on these operations. Find out more Collateral When banks borrow from us, they have to provide adequate collateral as a security. Want to know which collateral we accept? Looking for statistics on the collateral we have received? More information on collateral COVID-19 Our response to the pandemic Our measures Transparency Learn more about the reasoning behind our monetary policy decisions and about collaborating across Europe Monetary policy accounts We publish accounts of the Governing Council meetings in which monetary policy decisions are taken. These documents provide a summary of the discussions that took place. Monetary policy accounts Economic Bulletin The Economic Bulletin provides additional insight into the economic, financial and monetary developments that form the basis for our monetary policy decisions. Read more Market contact groups We have set up various market contact groups to guarantee that the implementation and transmission of our policies is smooth and efficient. The groups also let us talk to a range of market participants and follow developments in global financial markets and broader financing conditions in the euro area more closely. Market contact groups Public consultations We regularly seek input on decisions and initiatives affecting financial markets. This direct engagement lets us benefit from the insights of people involved or interested in these markets. See our ongoing and past public consultations Not an expert? Check out our explainer Learn more What is monetary policy? All pages in this section Are you happy with this page? Yes No What made you unhappy? Page not working Information not useful Design not attractive Something else Thank you for letting us know! Useful links About us Work with us Explainers Press photos Contacts Where to find us Using our site Disclaimer & Copyright Technical updates Responsible disclosure Corporate Policies Data Protection Privacy statement for the website Cookies policy Accessibility statement Language policy Site directory Copyright 2026, European Central Bank Follow us Our website uses cookies We use functional cookies to store user preferences; analytics cookies to improve website performance; third-party cookies set by third-party services integrated into the website. You have the choice to accept or reject them. For more information or to review your preference on the cookies and server logs we use, we invite you to: Read our privacy statement Learn more about how we use cookies I understand and I accept the use of cookies I do not accept the use of cookies Thank you! Thank you! We have updated our privacy policy We are always working to improve this website for our users. To do this, we use the anonymous data provided by cookies. See what has changed in our privacy policy I understand and I accept the use of cookies I do not accept the use of cookies Your cookie preference has expired We are always working to improve this website for our users. To do this, we use the anonymous data provided by cookies. Learn more about how we use cookies I understand and I accept the use of cookies I do not accept the use of cookies This feature requires cookies. Modify"
    },
    {
      "document_id": "bis-quarterly-2024-09",
      "title": "BIS Quarterly Review September 2024",
      "source": "https://www.bis.org/publ/qtrpdf/r_qt2409.htm",
      "content": "BIS Quarterly Review, September 2024 BIS Quarterly Review, September 2024 The BIS Quarterly Review includes analysis on recent developments in financial markets, life insurance, global alignment and trade, capital flows to EMEs and global banking statistics. BIS Quarterly Review | 16 September 2024 PDF full text (2 MB) | 94 pages Related information Conventions used in the BIS Quarterly Review Data behind all graphs Media Briefing Recent Quarterly Review special features Top Share this page Stay connected Follow us Sign up to receive email alerts About BIS Sitemap FAQ Contact Careers Translations Legal information Terms and conditions Copyright and permissions Privacy notice Cookies notice Email scam warning"
    },
    {
      "document_id": "fredblog-yield-curve",
      "title": "FRED Blog: Data Behind Yield Curve Inversions",
      "source": "https://fredblog.stlouisfed.org/2018/10/the-data-behind-the-fear-of-yield-curve-inversions/",
      "content": "The data behind the fear of yield curve inversions | FRED Blog Skip to main content Federal Reserve Economic Data Explore Our Apps FRED Tools and resources to find and use economic data worldwide FRASER U.S. financial, economic, and banking history ALFRED Vintages of economic data from specific dates in history CASSIDI View banking market concentrations and perform HHI analysis Release Calendar Tools FRED Add-in for Excel FRED API FRED Mobile Apps News Blog About What is FRED Tutorials Digital Badges Contact Us My Account Explore Our Apps Explore Our Apps FRED Tools and resources to find and use economic data worldwide FRASER U.S. financial, economic, and banking history ALFRED Vintages of economic data from specific dates in history CASSIDI View banking market concentrations and perform HHI analysis STL Fed Home Page Release Calendar Tools FRED Add-in for Excel FRED API FRED Mobile Apps News Blog About What is FRED Tutorials Digital Badges Contact Us Search FRED Blog Search for: Recent Posts Newly added daily data from NASDAQ The ups and downs of military pay US-India trade Total employment changes by thousands, while millions change jobs every month FOMC Summary of Economic Projections, March 2026 Recent St. Louis Fed research Newly added daily data from NASDAQ The ups and downs of military pay : Military vs. civilian government pay over the past 25 years US-India trade Total employment changes by thousands, while millions change jobs every month FOMC Summary of Economic Projections, March 2026 Archives April 2026 March 2026 February 2026 January 2026 December 2025 November 2025 October 2025 September 2025 August 2025 July 2025 June 2025 May 2025 April 2025 March 2025 February 2025 January 2025 December 2024 November 2024 October 2024 September 2024 August 2024 July 2024 June 2024 May 2024 April 2024 March 2024 February 2024 January 2024 December 2023 November 2023 October 2023 September 2023 August 2023 July 2023 June 2023 May 2023 April 2023 March 2023 February 2023 January 2023 December 2022 November 2022 October 2022 September 2022 August 2022 July 2022 June 2022 May 2022 April 2022 March 2022 February 2022 January 2022 December 2021 November 2021 October 2021 September 2021 August 2021 July 2021 June 2021 May 2021 April 2021 March 2021 February 2021 January 2021 December 2020 November 2020 October 2020 September 2020 August 2020 July 2020 June 2020 May 2020 April 2020 March 2020 February 2020 January 2020 December 2019 November 2019 October 2019 September 2019 August 2019 July 2019 June 2019 May 2019 April 2019 March 2019 February 2019 January 2019 December 2018 November 2018 October 2018 September 2018 August 2018 July 2018 June 2018 May 2018 April 2018 March 2018 February 2018 January 2018 December 2017 November 2017 October 2017 September 2017 August 2017 July 2017 June 2017 May 2017 April 2017 March 2017 February 2017 January 2017 December 2016 November 2016 October 2016 September 2016 August 2016 July 2016 June 2016 May 2016 April 2016 March 2016 February 2016 January 2016 December 2015 November 2015 October 2015 September 2015 August 2015 July 2015 June 2015 May 2015 April 2015 March 2015 February 2015 January 2015 December 2014 November 2014 October 2014 September 2014 August 2014 July 2014 June 2014 May 2014 April 2014 March 2014 The FRED ® Blog The data behind the fear of yield curve inversions Posted on October 11, 2018 FRED can help us make sense of the recent discussions about an inverted yield curve. But first, some definitions to get us started: The yield curve is the difference (or spread) between the yield on the 10-year Treasury bond and the yield on a shorter-term Treasury bond—for example, the 3-month or the 1-year. The yield curve is flattening if short-term rates are increasing relative to long-term rates, which is what’s been happening lately. The yield curve is inverted if short-term rates exceed long-term rates, making the spread negative. Inverted yield curves have historically been reliable predictors of impending recessions, which is why people are paying so much attention to the yield curve now. This FRED graph effectively illustrates that every recession since 1957 has been preceded by a yield curve inversion. (Note that the lag between the inversion and a recession varies: With the 10-year and 1-year yields, the lag is between 8 and 19 months, with an average of about 13 months.) A common interpretation is that the yield curve measures investors’ expectations of economic growth in the current period compared with economic growth in the future. According to this interpretation, a yield curve inversion implies that investors expect current economic growth to exceed future economic growth, indicating a recession is likely. Of course, some question the strength of the relationship between U.S. yield curves and recessions. The graph shows that, in 1965, the yield curve inverted but a recession didn’t closely follow. So, although yield curve inversions are good predictors of recessions, they’re not perfectly correlated and the exact relationship isn’t completely understood. In December 2013, the spread between long and short rates was very close to 3 percent. In September 2018, the spread was 0.44 percent for the 10-year and 1-year yields and 0.87 percent for the 10-year and 3-month yields. If the yield curve were to continue its downward trend from its previous high in December 2013, the yield curve would invert in August 2019 (using the 10-year and 1-year yields). Historically, this would predict a recession sometime in 2020. As the yield curve flattens, we can expect economists and financial markets will closely monitor its level and make many predictions about whether and when a recession will follow. How this graph was created : On the FRED homepage under the search box, use the “Browse data by…” option to search under “Category.” From there, select “Interest Rates” under “Money, Banking, & Finance.” Select “Treasury Constant Maturity.” Find and select the monthly “10-Year Treasury Constant Maturity Rate” series. From the “Edit Graph” menu, use the “Customize data” section to search for “1-Year Treasury Constant Maturity Rate” and select the option with “Monthly, Percent, Not Seasonally Adjusted” and add to the graph. The latter series is labeled as series “b.” Under “Customize data,” type a-b into “Formula” box and select “Apply.” Now select “Add Line” and follow this same process using “3-Month Treasury Bill: Secondary Market Rate” as the “b” series. Suggested by Matthew Famiglietti and Carlos Garriga . View on FRED, series used in this post: GS1 , GS10 , TB3MS Back to Top Filter 0 Subscribe to the FRED newsletter Subscribe Follow us Saint Louis Fed linkedin page Saint Louis Fed facebook page Saint Louis Fed X page Saint Louis Fed YouTube page Need Help? Questions or Comments FRED Help Legal Privacy Notice & Policy"
    }
  ]
}